realtouch.py
realtouch-0.1.10.dist-info/LICENSE
realtouch-0.1.10.dist-info/METADATA
realtouch-0.1.10.dist-info/WHEEL
realtouch-0.1.10.dist-info/top_level.txt
realtouch-0.1.10.dist-info/RECORD
