Metadata-Version: 2.1
Name: realtouch
Version: 0.1.10
Summary: realTouch Robot SDK
Home-page: https://realtouch.dev
Author: realTouch Dev
Author-email: contact@realtouch.dev
License: UNKNOWN
Platform: UNKNOWN
Classifier: License :: OSI Approved :: GNU General Public License v3 (GPLv3)
Classifier: Intended Audience :: Developers
Classifier: Programming Language :: Python :: 3.10
Classifier: Programming Language :: Python :: 3.11
Requires-Python: >=3.10
License-File: LICENSE
Requires-Dist: requests
Requires-Dist: loguru
Requires-Dist: numpy
Requires-Dist: opencv-python
